{
  "version": "0.4.1",
  "description": "Yet another repository management with auto-attaching profiles",
  "homepage": "https://github.com/siketyan/ghr",
  "license": {
    "identifier": "MIT",
    "url": "https://github.com/siketyan/ghr/blob/main/LICENCE.md"
  },
  "architecture": {
    "64bit": {
      "url": "https://github.com/siketyan/ghr/releases/download/v0.4.1/ghr-x86_64-pc-windows-msvc.tar.gz",
      "hash": "fe90a60940f89504f5b5812998fa72320f3f137bc6f5dbd0a581e0ee05005fce"
    }
  },
  "bin": "ghr.exe"
}
